pypisumtest01/__init__.py
pypisumtest01-0.0.1.dist-info/LICENSE.txt
pypisumtest01-0.0.1.dist-info/METADATA
pypisumtest01-0.0.1.dist-info/WHEEL
pypisumtest01-0.0.1.dist-info/top_level.txt
pypisumtest01-0.0.1.dist-info/RECORD
